{
  "id": "00000000-0000-0000-0000-000000000000",
  "prevId": "",
  "version": "7",
  "dialect": "postgresql",
  "tables": {
    "public.ContactMessage": {
      "name": "ContactMessage",
      "schema": "",
      "columns": {
        "id": {
          "name": "id",
          "type": "text",
          "primaryKey": true,
          "notNull": true
        },
        "fromEmail": {
          "name": "fromEmail",
          "type": "varchar(255)",
          "primaryKey": false,
          "notNull": true
        },
        "subject": {
          "name": "subject",
          "type": "varchar(255)",
          "primaryKey": false,
          "notNull": true,
          "default": "'No subject'"
        },
        "message": {
          "name": "message",
          "type": "text",
          "primaryKey": false,
          "notNull": true
        },
        "createdAt": {
          "name": "createdAt",
          "type": "timestamp(3)",
          "primaryKey": false,
          "notNull": true,
          "default": "now()"
        },
        "updatedAt": {
          "name": "updatedAt",
          "type": "timestamp(3)",
          "primaryKey": false,
          "notNull": true
        }
      },
      "indexes": {},
      "foreignKeys": {},
      "compositePrimaryKeys": {},
      "uniqueConstraints": {},
      "checkConstraints": {},
      "policies": {},
      "isRLSEnabled": false
    },
    "public.chatBotInteraction": {
      "name": "chatBotInteraction",
      "schema": "",
      "columns": {
        "id": {
          "name": "id",
          "type": "text",
          "primaryKey": true,
          "notNull": true
        },
        "day": {
          "name": "day",
          "type": "text",
          "primaryKey": false,
          "notNull": true
        },
        "count": {
          "name": "count",
          "type": "integer",
          "primaryKey": false,
          "notNull": true,
          "default": 1
        },
        "userId": {
          "name": "userId",
          "type": "text",
          "primaryKey": false,
          "notNull": true
        }
      },
      "indexes": {
        "chatBotInteraction_day_userId_idx": {
          "name": "chatBotInteraction_day_userId_idx",
          "columns": [
            {
              "expression": "day",
              "asc": true,
              "nulls": "last",
              "opclass": "text_ops",
              "isExpression": false
            },
            {
              "expression": "userId",
              "asc": true,
              "nulls": "last",
              "opclass": "text_ops",
              "isExpression": false
            }
          ],
          "isUnique": false,
          "concurrently": false,
          "method": "btree",
          "with": {}
        },
        "chatBotInteraction_day_userId_key": {
          "name": "chatBotInteraction_day_userId_key",
          "columns": [
            {
              "expression": "day",
              "asc": true,
              "nulls": "last",
              "opclass": "text_ops",
              "isExpression": false
            },
            {
              "expression": "userId",
              "asc": true,
              "nulls": "last",
              "opclass": "text_ops",
              "isExpression": false
            }
          ],
          "isUnique": true,
          "concurrently": false,
          "method": "btree",
          "with": {}
        },
        "chatBotInteraction_userId_key": {
          "name": "chatBotInteraction_userId_key",
          "columns": [
            {
              "expression": "userId",
              "asc": true,
              "nulls": "last",
              "opclass": "text_ops",
              "isExpression": false
            }
          ],
          "isUnique": true,
          "concurrently": false,
          "method": "btree",
          "with": {}
        }
      },
      "foreignKeys": {
        "chatBotInteraction_userId_fkey": {
          "name": "chatBotInteraction_userId_fkey",
          "tableFrom": "chatBotInteraction",
          "tableTo": "User",
          "schemaTo": "public",
          "columnsFrom": [
            "userId"
          ],
          "columnsTo": [
            "id"
          ],
          "onDelete": "restrict",
          "onUpdate": "cascade"
        }
      },
      "compositePrimaryKeys": {},
      "uniqueConstraints": {},
      "checkConstraints": {},
      "policies": {},
      "isRLSEnabled": false
    },
    "public.Subscription": {
      "name": "Subscription",
      "schema": "",
      "columns": {
        "id": {
          "name": "id",
          "type": "text",
          "primaryKey": true,
          "notNull": true
        },
        "userId": {
          "name": "userId",
          "type": "text",
          "primaryKey": false,
          "notNull": true
        },
        "paddleSubscriptionId": {
          "name": "paddleSubscriptionId",
          "type": "text",
          "primaryKey": false,
          "notNull": true
        },
        "customerID": {
          "name": "customerID",
          "type": "text",
          "primaryKey": false,
          "notNull": true
        },
        "addressId": {
          "name": "addressId",
          "type": "text",
          "primaryKey": false,
          "notNull": true
        },
        "businessId": {
          "name": "businessId",
          "type": "text",
          "primaryKey": false,
          "notNull": false
        },
        "createdAt": {
          "name": "createdAt",
          "type": "timestamp(3)",
          "primaryKey": false,
          "notNull": true,
          "default": "now()"
        },
        "updatedAt": {
          "name": "updatedAt",
          "type": "timestamp(3)",
          "primaryKey": false,
          "notNull": true
        },
        "startedAt": {
          "name": "startedAt",
          "type": "timestamp(3)",
          "primaryKey": false,
          "notNull": true
        },
        "endedAt": {
          "name": "endedAt",
          "type": "timestamp(3)",
          "primaryKey": false,
          "notNull": false
        },
        "nextBilledAt": {
          "name": "nextBilledAt",
          "type": "timestamp(3)",
          "primaryKey": false,
          "notNull": false
        },
        "pausedAt": {
          "name": "pausedAt",
          "type": "timestamp(3)",
          "primaryKey": false,
          "notNull": false
        },
        "canceledAt": {
          "name": "canceledAt",
          "type": "timestamp(3)",
          "primaryKey": false,
          "notNull": false
        },
        "status": {
          "name": "status",
          "type": "SubscriptionStatus",
          "typeSchema": "public",
          "primaryKey": false,
          "notNull": true
        },
        "billingInterval": {
          "name": "billingInterval",
          "type": "text",
          "primaryKey": false,
          "notNull": true
        },
        "billingFrequency": {
          "name": "billingFrequency",
          "type": "integer",
          "primaryKey": false,
          "notNull": true
        },
        "planId": {
          "name": "planId",
          "type": "text",
          "primaryKey": false,
          "notNull": true
        }
      },
      "indexes": {},
      "foreignKeys": {
        "Subscription_userId_fkey": {
          "name": "Subscription_userId_fkey",
          "tableFrom": "Subscription",
          "tableTo": "User",
          "schemaTo": "public",
          "columnsFrom": [
            "userId"
          ],
          "columnsTo": [
            "id"
          ],
          "onDelete": "restrict",
          "onUpdate": "cascade"
        }
      },
      "compositePrimaryKeys": {},
      "uniqueConstraints": {
        "Subscription_userId_key": {
          "columns": [
            "userId"
          ],
          "nullsNotDistinct": false,
          "name": "Subscription_userId_key"
        },
        "Subscription_paddleSubscriptionId_key": {
          "columns": [
            "paddleSubscriptionId"
          ],
          "nullsNotDistinct": false,
          "name": "Subscription_paddleSubscriptionId_key"
        }
      },
      "checkConstraints": {},
      "policies": {},
      "isRLSEnabled": false
    },
    "public._ToEmails": {
      "name": "_ToEmails",
      "schema": "",
      "columns": {
        "A": {
          "name": "A",
          "type": "text",
          "primaryKey": false,
          "notNull": true
        },
        "B": {
          "name": "B",
          "type": "text",
          "primaryKey": false,
          "notNull": true
        }
      },
      "indexes": {
        "_ToEmails_AB_unique": {
          "name": "_ToEmails_AB_unique",
          "columns": [
            {
              "expression": "A",
              "asc": true,
              "nulls": "last",
              "opclass": "text_ops",
              "isExpression": false
            },
            {
              "expression": "B",
              "asc": true,
              "nulls": "last",
              "opclass": "text_ops",
              "isExpression": false
            }
          ],
          "isUnique": true,
          "concurrently": false,
          "method": "btree",
          "with": {}
        },
        "_ToEmails_B_index": {
          "name": "_ToEmails_B_index",
          "columns": [
            {
              "expression": "B",
              "asc": true,
              "nulls": "last",
              "opclass": "text_ops",
              "isExpression": false
            }
          ],
          "isUnique": false,
          "concurrently": false,
          "method": "btree",
          "with": {}
        }
      },
      "foreignKeys": {
        "_ToEmails_A_fkey": {
          "name": "_ToEmails_A_fkey",
          "tableFrom": "_ToEmails",
          "tableTo": "Email",
          "schemaTo": "public",
          "columnsFrom": [
            "A"
          ],
          "columnsTo": [
            "id"
          ],
          "onDelete": "cascade",
          "onUpdate": "cascade"
        },
        "_ToEmails_B_fkey": {
          "name": "_ToEmails_B_fkey",
          "tableFrom": "_ToEmails",
          "tableTo": "EmailAddress",
          "schemaTo": "public",
          "columnsFrom": [
            "B"
          ],
          "columnsTo": [
            "id"
          ],
          "onDelete": "cascade",
          "onUpdate": "cascade"
        }
      },
      "compositePrimaryKeys": {},
      "uniqueConstraints": {},
      "checkConstraints": {},
      "policies": {},
      "isRLSEnabled": false
    },
    "public._ReplyToEmails": {
      "name": "_ReplyToEmails",
      "schema": "",
      "columns": {
        "A": {
          "name": "A",
          "type": "text",
          "primaryKey": false,
          "notNull": true
        },
        "B": {
          "name": "B",
          "type": "text",
          "primaryKey": false,
          "notNull": true
        }
      },
      "indexes": {
        "_ReplyToEmails_AB_unique": {
          "name": "_ReplyToEmails_AB_unique",
          "columns": [
            {
              "expression": "A",
              "asc": true,
              "nulls": "last",
              "opclass": "text_ops",
              "isExpression": false
            },
            {
              "expression": "B",
              "asc": true,
              "nulls": "last",
              "opclass": "text_ops",
              "isExpression": false
            }
          ],
          "isUnique": true,
          "concurrently": false,
          "method": "btree",
          "with": {}
        },
        "_ReplyToEmails_B_index": {
          "name": "_ReplyToEmails_B_index",
          "columns": [
            {
              "expression": "B",
              "asc": true,
              "nulls": "last",
              "opclass": "text_ops",
              "isExpression": false
            }
          ],
          "isUnique": false,
          "concurrently": false,
          "method": "btree",
          "with": {}
        }
      },
      "foreignKeys": {
        "_ReplyToEmails_A_fkey": {
          "name": "_ReplyToEmails_A_fkey",
          "tableFrom": "_ReplyToEmails",
          "tableTo": "Email",
          "schemaTo": "public",
          "columnsFrom": [
            "A"
          ],
          "columnsTo": [
            "id"
          ],
          "onDelete": "cascade",
          "onUpdate": "cascade"
        },
        "_ReplyToEmails_B_fkey": {
          "name": "_ReplyToEmails_B_fkey",
          "tableFrom": "_ReplyToEmails",
          "tableTo": "EmailAddress",
          "schemaTo": "public",
          "columnsFrom": [
            "B"
          ],
          "columnsTo": [
            "id"
          ],
          "onDelete": "cascade",
          "onUpdate": "cascade"
        }
      },
      "compositePrimaryKeys": {},
      "uniqueConstraints": {},
      "checkConstraints": {},
      "policies": {},
      "isRLSEnabled": false
    },
    "public._CcEmails": {
      "name": "_CcEmails",
      "schema": "",
      "columns": {
        "A": {
          "name": "A",
          "type": "text",
          "primaryKey": false,
          "notNull": true
        },
        "B": {
          "name": "B",
          "type": "text",
          "primaryKey": false,
          "notNull": true
        }
      },
      "indexes": {
        "_CcEmails_AB_unique": {
          "name": "_CcEmails_AB_unique",
          "columns": [
            {
              "expression": "A",
              "asc": true,
              "nulls": "last",
              "opclass": "text_ops",
              "isExpression": false
            },
            {
              "expression": "B",
              "asc": true,
              "nulls": "last",
              "opclass": "text_ops",
              "isExpression": false
            }
          ],
          "isUnique": true,
          "concurrently": false,
          "method": "btree",
          "with": {}
        },
        "_CcEmails_B_index": {
          "name": "_CcEmails_B_index",
          "columns": [
            {
              "expression": "B",
              "asc": true,
              "nulls": "last",
              "opclass": "text_ops",
              "isExpression": false
            }
          ],
          "isUnique": false,
          "concurrently": false,
          "method": "btree",
          "with": {}
        }
      },
      "foreignKeys": {
        "_CcEmails_A_fkey": {
          "name": "_CcEmails_A_fkey",
          "tableFrom": "_CcEmails",
          "tableTo": "Email",
          "schemaTo": "public",
          "columnsFrom": [
            "A"
          ],
          "columnsTo": [
            "id"
          ],
          "onDelete": "cascade",
          "onUpdate": "cascade"
        },
        "_CcEmails_B_fkey": {
          "name": "_CcEmails_B_fkey",
          "tableFrom": "_CcEmails",
          "tableTo": "EmailAddress",
          "schemaTo": "public",
          "columnsFrom": [
            "B"
          ],
          "columnsTo": [
            "id"
          ],
          "onDelete": "cascade",
          "onUpdate": "cascade"
        }
      },
      "compositePrimaryKeys": {},
      "uniqueConstraints": {},
      "checkConstraints": {},
      "policies": {},
      "isRLSEnabled": false
    },
    "public._BccEmails": {
      "name": "_BccEmails",
      "schema": "",
      "columns": {
        "A": {
          "name": "A",
          "type": "text",
          "primaryKey": false,
          "notNull": true
        },
        "B": {
          "name": "B",
          "type": "text",
          "primaryKey": false,
          "notNull": true
        }
      },
      "indexes": {
        "_BccEmails_AB_unique": {
          "name": "_BccEmails_AB_unique",
          "columns": [
            {
              "expression": "A",
              "asc": true,
              "nulls": "last",
              "opclass": "text_ops",
              "isExpression": false
            },
            {
              "expression": "B",
              "asc": true,
              "nulls": "last",
              "opclass": "text_ops",
              "isExpression": false
            }
          ],
          "isUnique": true,
          "concurrently": false,
          "method": "btree",
          "with": {}
        },
        "_BccEmails_B_index": {
          "name": "_BccEmails_B_index",
          "columns": [
            {
              "expression": "B",
              "asc": true,
              "nulls": "last",
              "opclass": "text_ops",
              "isExpression": false
            }
          ],
          "isUnique": false,
          "concurrently": false,
          "method": "btree",
          "with": {}
        }
      },
      "foreignKeys": {
        "_BccEmails_A_fkey": {
          "name": "_BccEmails_A_fkey",
          "tableFrom": "_BccEmails",
          "tableTo": "Email",
          "schemaTo": "public",
          "columnsFrom": [
            "A"
          ],
          "columnsTo": [
            "id"
          ],
          "onDelete": "cascade",
          "onUpdate": "cascade"
        },
        "_BccEmails_B_fkey": {
          "name": "_BccEmails_B_fkey",
          "tableFrom": "_BccEmails",
          "tableTo": "EmailAddress",
          "schemaTo": "public",
          "columnsFrom": [
            "B"
          ],
          "columnsTo": [
            "id"
          ],
          "onDelete": "cascade",
          "onUpdate": "cascade"
        }
      },
      "compositePrimaryKeys": {},
      "uniqueConstraints": {},
      "checkConstraints": {},
      "policies": {},
      "isRLSEnabled": false
    },
    "public.Thread": {
      "name": "Thread",
      "schema": "",
      "columns": {
        "id": {
          "name": "id",
          "type": "text",
          "primaryKey": true,
          "notNull": true
        },
        "subject": {
          "name": "subject",
          "type": "text",
          "primaryKey": false,
          "notNull": true
        },
        "lastMessageDate": {
          "name": "lastMessageDate",
          "type": "timestamp(3)",
          "primaryKey": false,
          "notNull": true
        },
        "participantsIds": {
          "name": "participantsIds",
          "type": "text[]",
          "primaryKey": false,
          "notNull": true
        },
        "accountId": {
          "name": "accountId",
          "type": "text",
          "primaryKey": false,
          "notNull": false
        },
        "done": {
          "name": "done",
          "type": "boolean",
          "primaryKey": false,
          "notNull": true,
          "default": false
        },
        "inboxStatus": {
          "name": "inboxStatus",
          "type": "boolean",
          "primaryKey": false,
          "notNull": true,
          "default": true
        },
        "draftStatus": {
          "name": "draftStatus",
          "type": "boolean",
          "primaryKey": false,
          "notNull": true,
          "default": false
        },
        "sentStatus": {
          "name": "sentStatus",
          "type": "boolean",
          "primaryKey": false,
          "notNull": true,
          "default": false
        }
      },
      "indexes": {
        "Thread_accountId_idx": {
          "name": "Thread_accountId_idx",
          "columns": [
            {
              "expression": "accountId",
              "asc": true,
              "nulls": "last",
              "opclass": "text_ops",
              "isExpression": false
            }
          ],
          "isUnique": false,
          "concurrently": false,
          "method": "btree",
          "with": {}
        },
        "Thread_done_idx": {
          "name": "Thread_done_idx",
          "columns": [
            {
              "expression": "done",
              "asc": true,
              "nulls": "last",
              "opclass": "bool_ops",
              "isExpression": false
            }
          ],
          "isUnique": false,
          "concurrently": false,
          "method": "btree",
          "with": {}
        },
        "Thread_draftStatus_idx": {
          "name": "Thread_draftStatus_idx",
          "columns": [
            {
              "expression": "draftStatus",
              "asc": true,
              "nulls": "last",
              "opclass": "bool_ops",
              "isExpression": false
            }
          ],
          "isUnique": false,
          "concurrently": false,
          "method": "btree",
          "with": {}
        },
        "Thread_inboxStatus_idx": {
          "name": "Thread_inboxStatus_idx",
          "columns": [
            {
              "expression": "inboxStatus",
              "asc": true,
              "nulls": "last",
              "opclass": "bool_ops",
              "isExpression": false
            }
          ],
          "isUnique": false,
          "concurrently": false,
          "method": "btree",
          "with": {}
        },
        "Thread_lastMessageDate_idx": {
          "name": "Thread_lastMessageDate_idx",
          "columns": [
            {
              "expression": "lastMessageDate",
              "asc": true,
              "nulls": "last",
              "opclass": "timestamp_ops",
              "isExpression": false
            }
          ],
          "isUnique": false,
          "concurrently": false,
          "method": "btree",
          "with": {}
        },
        "Thread_sentStatus_idx": {
          "name": "Thread_sentStatus_idx",
          "columns": [
            {
              "expression": "sentStatus",
              "asc": true,
              "nulls": "last",
              "opclass": "bool_ops",
              "isExpression": false
            }
          ],
          "isUnique": false,
          "concurrently": false,
          "method": "btree",
          "with": {}
        }
      },
      "foreignKeys": {
        "Thread_accountId_fkey": {
          "name": "Thread_accountId_fkey",
          "tableFrom": "Thread",
          "tableTo": "Account",
          "schemaTo": "public",
          "columnsFrom": [
            "accountId"
          ],
          "columnsTo": [
            "id"
          ],
          "onDelete": "set null",
          "onUpdate": "cascade"
        }
      },
      "compositePrimaryKeys": {},
      "uniqueConstraints": {},
      "checkConstraints": {},
      "policies": {},
      "isRLSEnabled": false
    },
    "public.EmailAttachment": {
      "name": "EmailAttachment",
      "schema": "",
      "columns": {
        "id": {
          "name": "id",
          "type": "text",
          "primaryKey": true,
          "notNull": true
        },
        "name": {
          "name": "name",
          "type": "text",
          "primaryKey": false,
          "notNull": true
        },
        "mimeType": {
          "name": "mimeType",
          "type": "text",
          "primaryKey": false,
          "notNull": true
        },
        "size": {
          "name": "size",
          "type": "integer",
          "primaryKey": false,
          "notNull": true
        },
        "inline": {
          "name": "inline",
          "type": "boolean",
          "primaryKey": false,
          "notNull": true
        },
        "contentId": {
          "name": "contentId",
          "type": "text",
          "primaryKey": false,
          "notNull": false
        },
        "content": {
          "name": "content",
          "type": "text",
          "primaryKey": false,
          "notNull": false
        },
        "contentLocation": {
          "name": "contentLocation",
          "type": "text",
          "primaryKey": false,
          "notNull": false
        },
        "emailId": {
          "name": "emailId",
          "type": "text",
          "primaryKey": false,
          "notNull": true
        }
      },
      "indexes": {},
      "foreignKeys": {
        "EmailAttachment_emailId_fkey": {
          "name": "EmailAttachment_emailId_fkey",
          "tableFrom": "EmailAttachment",
          "tableTo": "Email",
          "schemaTo": "public",
          "columnsFrom": [
            "emailId"
          ],
          "columnsTo": [
            "id"
          ],
          "onDelete": "restrict",
          "onUpdate": "cascade"
        }
      },
      "compositePrimaryKeys": {},
      "uniqueConstraints": {},
      "checkConstraints": {},
      "policies": {},
      "isRLSEnabled": false
    },
    "public.Email": {
      "name": "Email",
      "schema": "",
      "columns": {
        "id": {
          "name": "id",
          "type": "text",
          "primaryKey": true,
          "notNull": true
        },
        "threadId": {
          "name": "threadId",
          "type": "text",
          "primaryKey": false,
          "notNull": true
        },
        "createdTime": {
          "name": "createdTime",
          "type": "timestamp(3)",
          "primaryKey": false,
          "notNull": true
        },
        "lastModifiedTime": {
          "name": "lastModifiedTime",
          "type": "timestamp(3)",
          "primaryKey": false,
          "notNull": true
        },
        "sentAt": {
          "name": "sentAt",
          "type": "timestamp(3)",
          "primaryKey": false,
          "notNull": true
        },
        "receivedAt": {
          "name": "receivedAt",
          "type": "timestamp(3)",
          "primaryKey": false,
          "notNull": true
        },
        "internetMessageId": {
          "name": "internetMessageId",
          "type": "text",
          "primaryKey": false,
          "notNull": true
        },
        "subject": {
          "name": "subject",
          "type": "text",
          "primaryKey": false,
          "notNull": true
        },
        "sysLabels": {
          "name": "sysLabels",
          "type": "text[]",
          "primaryKey": false,
          "notNull": true
        },
        "keywords": {
          "name": "keywords",
          "type": "text[]",
          "primaryKey": false,
          "notNull": true
        },
        "sysClassifications": {
          "name": "sysClassifications",
          "type": "text[]",
          "primaryKey": false,
          "notNull": true
        },
        "sensitivity": {
          "name": "sensitivity",
          "type": "Sensitivity",
          "typeSchema": "public",
          "primaryKey": false,
          "notNull": true,
          "default": "'normal'"
        },
        "meetingMessageMethod": {
          "name": "meetingMessageMethod",
          "type": "MeetingMessageMethod",
          "typeSchema": "public",
          "primaryKey": false,
          "notNull": false
        },
        "fromId": {
          "name": "fromId",
          "type": "text",
          "primaryKey": false,
          "notNull": true
        },
        "hasAttachments": {
          "name": "hasAttachments",
          "type": "boolean",
          "primaryKey": false,
          "notNull": true
        },
        "body": {
          "name": "body",
          "type": "text",
          "primaryKey": false,
          "notNull": false
        },
        "bodySnippet": {
          "name": "bodySnippet",
          "type": "text",
          "primaryKey": false,
          "notNull": false
        },
        "inReplyTo": {
          "name": "inReplyTo",
          "type": "text",
          "primaryKey": false,
          "notNull": false
        },
        "references": {
          "name": "references",
          "type": "text",
          "primaryKey": false,
          "notNull": false
        },
        "threadIndex": {
          "name": "threadIndex",
          "type": "text",
          "primaryKey": false,
          "notNull": false
        },
        "internetHeaders": {
          "name": "internetHeaders",
          "type": "jsonb[]",
          "primaryKey": false,
          "notNull": true
        },
        "nativeProperties": {
          "name": "nativeProperties",
          "type": "jsonb",
          "primaryKey": false,
          "notNull": false
        },
        "folderId": {
          "name": "folderId",
          "type": "text",
          "primaryKey": false,
          "notNull": false
        },
        "omitted": {
          "name": "omitted",
          "type": "text[]",
          "primaryKey": false,
          "notNull": true
        },
        "emailLabel": {
          "name": "emailLabel",
          "type": "EmailLabel",
          "typeSchema": "public",
          "primaryKey": false,
          "notNull": true,
          "default": "'inbox'"
        }
      },
      "indexes": {
        "Email_emailLabel_idx": {
          "name": "Email_emailLabel_idx",
          "columns": [
            {
              "expression": "emailLabel",
              "asc": true,
              "nulls": "last",
              "opclass": "enum_ops",
              "isExpression": false
            }
          ],
          "isUnique": false,
          "concurrently": false,
          "method": "btree",
          "with": {}
        },
        "Email_sentAt_idx": {
          "name": "Email_sentAt_idx",
          "columns": [
            {
              "expression": "sentAt",
              "asc": true,
              "nulls": "last",
              "opclass": "timestamp_ops",
              "isExpression": false
            }
          ],
          "isUnique": false,
          "concurrently": false,
          "method": "btree",
          "with": {}
        },
        "Email_threadId_idx": {
          "name": "Email_threadId_idx",
          "columns": [
            {
              "expression": "threadId",
              "asc": true,
              "nulls": "last",
              "opclass": "text_ops",
              "isExpression": false
            }
          ],
          "isUnique": false,
          "concurrently": false,
          "method": "btree",
          "with": {}
        }
      },
      "foreignKeys": {
        "Email_fromId_fkey": {
          "name": "Email_fromId_fkey",
          "tableFrom": "Email",
          "tableTo": "EmailAddress",
          "schemaTo": "public",
          "columnsFrom": [
            "fromId"
          ],
          "columnsTo": [
            "id"
          ],
          "onDelete": "restrict",
          "onUpdate": "cascade"
        },
        "Email_threadId_fkey": {
          "name": "Email_threadId_fkey",
          "tableFrom": "Email",
          "tableTo": "Thread",
          "schemaTo": "public",
          "columnsFrom": [
            "threadId"
          ],
          "columnsTo": [
            "id"
          ],
          "onDelete": "restrict",
          "onUpdate": "cascade"
        }
      },
      "compositePrimaryKeys": {},
      "uniqueConstraints": {},
      "checkConstraints": {},
      "policies": {},
      "isRLSEnabled": false
    },
    "public.EmailAddress": {
      "name": "EmailAddress",
      "schema": "",
      "columns": {
        "id": {
          "name": "id",
          "type": "text",
          "primaryKey": true,
          "notNull": true
        },
        "name": {
          "name": "name",
          "type": "text",
          "primaryKey": false,
          "notNull": false
        },
        "address": {
          "name": "address",
          "type": "text",
          "primaryKey": false,
          "notNull": true
        },
        "raw": {
          "name": "raw",
          "type": "text",
          "primaryKey": false,
          "notNull": false
        },
        "accountId": {
          "name": "accountId",
          "type": "text",
          "primaryKey": false,
          "notNull": true
        }
      },
      "indexes": {
        "EmailAddress_accountId_address_key": {
          "name": "EmailAddress_accountId_address_key",
          "columns": [
            {
              "expression": "accountId",
              "asc": true,
              "nulls": "last",
              "opclass": "text_ops",
              "isExpression": false
            },
            {
              "expression": "address",
              "asc": true,
              "nulls": "last",
              "opclass": "text_ops",
              "isExpression": false
            }
          ],
          "isUnique": true,
          "concurrently": false,
          "method": "btree",
          "with": {}
        }
      },
      "foreignKeys": {
        "EmailAddress_accountId_fkey": {
          "name": "EmailAddress_accountId_fkey",
          "tableFrom": "EmailAddress",
          "tableTo": "Account",
          "schemaTo": "public",
          "columnsFrom": [
            "accountId"
          ],
          "columnsTo": [
            "id"
          ],
          "onDelete": "restrict",
          "onUpdate": "cascade"
        }
      },
      "compositePrimaryKeys": {},
      "uniqueConstraints": {},
      "checkConstraints": {},
      "policies": {},
      "isRLSEnabled": false
    },
    "public.Account": {
      "name": "Account",
      "schema": "",
      "columns": {
        "id": {
          "name": "id",
          "type": "text",
          "primaryKey": true,
          "notNull": true
        },
        "userId": {
          "name": "userId",
          "type": "text",
          "primaryKey": false,
          "notNull": true
        },
        "emailAddress": {
          "name": "emailAddress",
          "type": "text",
          "primaryKey": false,
          "notNull": true
        },
        "accessToken": {
          "name": "accessToken",
          "type": "text",
          "primaryKey": false,
          "notNull": true
        },
        "name": {
          "name": "name",
          "type": "text",
          "primaryKey": false,
          "notNull": true
        },
        "oramaIndex": {
          "name": "oramaIndex",
          "type": "jsonb",
          "primaryKey": false,
          "notNull": false
        },
        "nextDeltaToken": {
          "name": "nextDeltaToken",
          "type": "text",
          "primaryKey": false,
          "notNull": false
        }
      },
      "indexes": {},
      "foreignKeys": {
        "Account_userId_fkey": {
          "name": "Account_userId_fkey",
          "tableFrom": "Account",
          "tableTo": "User",
          "schemaTo": "public",
          "columnsFrom": [
            "userId"
          ],
          "columnsTo": [
            "id"
          ],
          "onDelete": "restrict",
          "onUpdate": "cascade"
        }
      },
      "compositePrimaryKeys": {},
      "uniqueConstraints": {
        "Account_accessToken_key": {
          "columns": [
            "accessToken"
          ],
          "nullsNotDistinct": false,
          "name": "Account_accessToken_key"
        }
      },
      "checkConstraints": {},
      "policies": {},
      "isRLSEnabled": false
    },
    "public.User": {
      "name": "User",
      "schema": "",
      "columns": {
        "id": {
          "name": "id",
          "type": "text",
          "primaryKey": true,
          "notNull": true
        },
        "emailAddress": {
          "name": "emailAddress",
          "type": "text",
          "primaryKey": false,
          "notNull": true
        },
        "firstName": {
          "name": "firstName",
          "type": "text",
          "primaryKey": false,
          "notNull": false
        },
        "lastName": {
          "name": "lastName",
          "type": "text",
          "primaryKey": false,
          "notNull": false
        },
        "imageUrl": {
          "name": "imageUrl",
          "type": "text",
          "primaryKey": false,
          "notNull": false
        }
      },
      "indexes": {},
      "foreignKeys": {},
      "compositePrimaryKeys": {},
      "uniqueConstraints": {
        "User_emailAddress_key": {
          "columns": [
            "emailAddress"
          ],
          "nullsNotDistinct": false,
          "name": "User_emailAddress_key"
        }
      },
      "checkConstraints": {},
      "policies": {},
      "isRLSEnabled": false
    }
  },
  "enums": {
    "public.EmailLabel": {
      "name": "EmailLabel",
      "values": [
        "inbox",
        "sent",
        "draft"
      ],
      "schema": "public"
    },
    "public.MeetingMessageMethod": {
      "name": "MeetingMessageMethod",
      "values": [
        "request",
        "reply",
        "cancel",
        "counter",
        "other"
      ],
      "schema": "public"
    },
    "public.Sensitivity": {
      "name": "Sensitivity",
      "values": [
        "normal",
        "private",
        "personal",
        "confidential"
      ],
      "schema": "public"
    },
    "public.SubscriptionStatus": {
      "name": "SubscriptionStatus",
      "values": [
        "ACTIVE",
        "PAUSED",
        "CANCELLED",
        "EXPIRED",
        "PAST_DUE"
      ],
      "schema": "public"
    }
  },
  "schemas": {},
  "sequences": {},
  "roles": {},
  "policies": {},
  "views": {},
  "_meta": {
    "schemas": {},
    "tables": {},
    "columns": {}
  },
  "internal": {
    "tables": {
      "Thread": {
        "columns": {
          "participantsIds": {
            "isArray": true,
            "dimensions": 1,
            "rawType": "text"
          }
        }
      },
      "Email": {
        "columns": {
          "sysLabels": {
            "isArray": true,
            "dimensions": 1,
            "rawType": "text"
          },
          "keywords": {
            "isArray": true,
            "dimensions": 1,
            "rawType": "text"
          },
          "sysClassifications": {
            "isArray": true,
            "dimensions": 1,
            "rawType": "text"
          },
          "internetHeaders": {
            "isArray": true,
            "dimensions": 1,
            "rawType": "jsonb"
          },
          "omitted": {
            "isArray": true,
            "dimensions": 1,
            "rawType": "text"
          }
        }
      }
    }
  }
}